rpaudio-0.0.18.dist-info/METADATA
rpaudio-0.0.18.dist-info/WHEEL
rpaudio-0.0.18.dist-info/licenses/LICENSE
rpaudio/effects/__init__.pyi
rpaudio/exceptions/__init__.pyi
rpaudio/__init__.py
rpaudio/__init__.pyi
rpaudio/rpaudio.pyd
rpaudio-0.0.18.dist-info/RECORD
