Metadata-Version: 2.4
Name: rpaudio
Version: 0.0.18
Classifier: Programming Language :: Python :: 3
Classifier: License :: OSI Approved :: MIT License
Classifier: Operating System :: OS Independent
Requires-Dist: pytest <=8.3.2 ; extra == 'test'
Requires-Dist: pytest-asyncio ; extra == 'test'
Requires-Dist: pytest-json-report ; extra == 'test'
Requires-Dist: sphinx ; extra == 'docs'
Requires-Dist: sphinx-rtd-theme ; extra == 'docs'
Requires-Dist: sphinxcontrib-napoleon ; extra == 'docs'
Requires-Dist: sphinx-autodoc-typehints ; extra == 'docs'
Requires-Dist: sphinx-autoapi ; extra == 'docs'
Requires-Dist: maturin ; extra == 'docs'
Requires-Dist: maturin ; extra == 'dev'
Provides-Extra: test
Provides-Extra: docs
Provides-Extra: dev
License-File: LICENSE
Summary: Rust audio api binding for python
Author: Beaux44
Author-email: Ryan Skiles <r.p.skiles@gmail.com>
License: Apache-2.0
Requires-Python: >=3.8
Project-URL: Homepage, https://github.com/sockheadrps/rpaudio
Project-URL: Issues, https://github.com/sockheadrps/rpaudio/issues
